Workbook
Name __xlfn_SUMIFS: #N/A

Sheet Forecast_Data
A1: Nr. | B1: Pos. | C1: Unit | D1: Kunde | E1: Projekt | F1: Angebotsdatum | G1: Titel | H1: Pos.-Titel | I1: Art | J1: Abrechnungsart | K1: Auftrag Status | L1: Position Status | M1: PT | N1: Nettosumme | O1: Eintrittswahrsch. in % | P1: gewichtete Nettosumme | Q1: fakturiert | R1: gewichtet offen | S1: vollständig fakturiert | T1: Debitorenrechnungen | U1: Leistungszeitraum | W1: Anzahl Monate | X1: Forecasttyp | Y1: Rest | Z1: Abweichung | AA1: Warnung | AB1: Beschreibung Status | AD1: Month 1 | AE1: Month 2 | AF1: Month 3 | AG1: Month 4 | AH1: Month 5 | AI1: Month 6 | AJ1: Month 7 | AK1: Month 8 | AL1: Month 9 | AM1: Month 10 | AN1: Month 11 | AO1: Month 12 | AP1: Erfassungsdatum | AQ1: Entscheidungsdatum | AR1: Zahlplan | AS1: Ansprechpartner | AT1: Strukturelement | AU1: Bemerkung | AV1: ProjectID | AW1: visible | AX1: visibleID
A2: date | AC2: beauftragt | AD2: =SUMIFS(AD11:AD100000,$L11:$L100000,"=beauftragt",$AW11:$AW100000,1) -> 0 | AE2: =SUMIFS(AE11:AE100000,$L11:$L100000,"=beauftragt",$AW11:$AW100000,1) -> 0 | AF2: =SUMIFS(AF11:AF100000,$L11:$L100000,"=beauftragt",$AW11:$AW100000,1) -> 0 | AG2: =SUMIFS(AG11:AG100000,$L11:$L100000,"=beauftragt",$AW11:$AW100000,1) -> 0 | AH2: =SUMIFS(AH11:AH100000,$L11:$L100000,"=beauftragt",$AW11:$AW100000,1) -> 0 | AI2: =SUMIFS(AI11:AI100000,$L11:$L100000,"=beauftragt",$AW11:$AW100000,1) -> 0 | AJ2: =SUMIFS(AJ11:AJ100000,$L11:$L100000,"=beauftragt",$AW11:$AW100000,1) -> 0 | AK2: =SUMIFS(AK11:AK100000,$L11:$L100000,"=beauftragt",$AW11:$AW100000,1) -> 0 | ... AO2: =SUMIFS(AO11:AO100000,$L11:$L100000,"=beauftragt",$AW11:$AW100000,1) -> 0
AC3: gelegt | AD3: =SUMIFS(AD11:AD100000,$L11:$L100000,"=gelegt",$AW11:$AW100000,1) -> 0 | AE3: =SUMIFS(AE11:AE100000,$L11:$L100000,"=gelegt",$AW11:$AW100000,1) -> 0 | AF3: =SUMIFS(AF11:AF100000,$L11:$L100000,"=gelegt",$AW11:$AW100000,1) -> 0 | AG3: =SUMIFS(AG11:AG100000,$L11:$L100000,"=gelegt",$AW11:$AW100000,1) -> 0 | AH3: =SUMIFS(AH11:AH100000,$L11:$L100000,"=gelegt",$AW11:$AW100000,1) -> 0 | AI3: =SUMIFS(AI11:AI100000,$L11:$L100000,"=gelegt",$AW11:$AW100000,1) -> 0 | AJ3: =SUMIFS(AJ11:AJ100000,$L11:$L100000,"=gelegt",$AW11:$AW100000,1) -> 0 | AK3: =SUMIFS(AK11:AK100000,$L11:$L100000,"=gelegt",$AW11:$AW100000,1) -> 0 | ... AO3: =SUMIFS(AO11:AO100000,$L11:$L100000,"=gelegt",$AW11:$AW100000,1) -> 0
AC4: LOI | AD4: =SUMIFS(AD11:AD100000,$L11:$L100000,"=LOI",$AW11:$AW100000,1) -> 0 | AE4: =SUMIFS(AE11:AE100000,$L11:$L100000,"=LOI",$AW11:$AW100000,1) -> 0 | AF4: =SUMIFS(AF11:AF100000,$L11:$L100000,"=LOI",$AW11:$AW100000,1) -> 0 | AG4: =SUMIFS(AG11:AG100000,$L11:$L100000,"=LOI",$AW11:$AW100000,1) -> 0 | AH4: =SUMIFS(AH11:AH100000,$L11:$L100000,"=LOI",$AW11:$AW100000,1) -> 0 | AI4: =SUMIFS(AI11:AI100000,$L11:$L100000,"=LOI",$AW11:$AW100000,1) -> 0 | AJ4: =SUMIFS(AJ11:AJ100000,$L11:$L100000,"=LOI",$AW11:$AW100000,1) -> 0 | AK4: =SUMIFS(AK11:AK100000,$L11:$L100000,"=LOI",$AW11:$AW100000,1) -> 0 | ... AO4: =SUMIFS(AO11:AO100000,$L11:$L100000,"=LOI",$AW11:$AW100000,1) -> 0
AC5: in Erstellung | AD5: =SUMIFS(AD11:AD100000,$L11:$L100000,"=in Erstellung",$AW11:$AW100000,1) -> 0 | AE5: =SUMIFS(AE11:AE100000,$L11:$L100000,"=in Erstellung",$AW11:$AW100000,1) -> 0 | AF5: =SUMIFS(AF11:AF100000,$L11:$L100000,"=in Erstellung",$AW11:$AW100000,1) -> 0 | AG5: =SUMIFS(AG11:AG100000,$L11:$L100000,"=in Erstellung",$AW11:$AW100000,1) -> 0 | AH5: =SUMIFS(AH11:AH100000,$L11:$L100000,"=in Erstellung",$AW11:$AW100000,1) -> 0 | AI5: =SUMIFS(AI11:AI100000,$L11:$L100000,"=in Erstellung",$AW11:$AW100000,1) -> 0 | AJ5: =SUMIFS(AJ11:AJ100000,$L11:$L100000,"=in Erstellung",$AW11:$AW100000,1) -> 0 | AK5: =SUMIFS(AK11:AK100000,$L11:$L100000,"=in Erstellung",$AW11:$AW100000,1) -> 0 | ... AO5: =SUMIFS(AO11:AO100000,$L11:$L100000,"=in Erstellung",$AW11:$AW100000,1) -> 0
AC6: Potenzial | AD6: =SUMIFS(AD11:AD100000,$L11:$L100000,"=Potenzial",$AW11:$AW100000,1) -> 0 | AE6: =SUMIFS(AE11:AE100000,$L11:$L100000,"=Potenzial",$AW11:$AW100000,1) -> 0 | AF6: =SUMIFS(AF11:AF100000,$L11:$L100000,"=Potenzial",$AW11:$AW100000,1) -> 0 | AG6: =SUMIFS(AG11:AG100000,$L11:$L100000,"=Potenzial",$AW11:$AW100000,1) -> 0 | AH6: =SUMIFS(AH11:AH100000,$L11:$L100000,"=Potenzial",$AW11:$AW100000,1) -> 0 | AI6: =SUMIFS(AI11:AI100000,$L11:$L100000,"=Potenzial",$AW11:$AW100000,1) -> 0 | AJ6: =SUMIFS(AJ11:AJ100000,$L11:$L100000,"=Potenzial",$AW11:$AW100000,1) -> 0 | AK6: =SUMIFS(AK11:AK100000,$L11:$L100000,"=Potenzial",$AW11:$AW100000,1) -> 0 | ... AO6: =SUMIFS(AO11:AO100000,$L11:$L100000,"=Potenzial",$AW11:$AW100000,1) -> 0
AC7: Gesamt | AD7: =SUM(AD2:AD6) -> 0 | AE7: =SUM(AE2:AE6) -> 0 | AF7: =SUM(AF2:AF6) -> 0 | AG7: =SUM(AG2:AG6) -> 0 | AH7: =SUM(AH2:AH6) -> 0 | AI7: =SUM(AI2:AI6) -> 0 | AJ7: =SUM(AJ2:AJ6) -> 0 | AK7: =SUM(AK2:AK6) -> 0 | ... AO7: =SUM(AO2:AO6) -> 0
AC8: IST | AD8: =SUMIFS(Rechnungen!M:M, Rechnungen!$Z:$Z, TRUE) -> 0 | AE8: =SUMIFS(Rechnungen!N:N, Rechnungen!$Z:$Z, TRUE) -> 0 | AF8: =SUMIFS(Rechnungen!O:O, Rechnungen!$Z:$Z, TRUE) -> 0 | AG8: =SUMIFS(Rechnungen!P:P, Rechnungen!$Z:$Z, TRUE) -> 0 | AH8: =SUMIFS(Rechnungen!Q:Q, Rechnungen!$Z:$Z, TRUE) -> 0 | AI8: =SUMIFS(Rechnungen!R:R, Rechnungen!$Z:$Z, TRUE) -> 0 | AJ8: =SUMIFS(Rechnungen!S:S, Rechnungen!$Z:$Z, TRUE) -> 0 | AK8: =SUMIFS(Rechnungen!T:T, Rechnungen!$Z:$Z, TRUE) -> 0 | AL8: =SUMIFS(Rechnungen!U:U, Rechnungen!$Z:$Z, TRUE) -> 0 | AM8: =SUMIFS(Rechnungen!V:V, Rechnungen!$Z:$Z, TRUE) -> 0 | AN8: =SUMIFS(Rechnungen!W:W, Rechnungen!$Z:$Z, TRUE) -> 0 | AO8: =SUMIFS(Rechnungen!X:X, Rechnungen!$Z:$Z, TRUE) -> 0
AC9: PLAN | AD9: =Planning_Data!AD7 -> 0 | AE9: =Planning_Data!AE7 -> 0 | AF9: =Planning_Data!AF7 -> 0 | AG9: =Planning_Data!AG7 -> 0 | AH9: =Planning_Data!AH7 -> 0 | AI9: =Planning_Data!AI7 -> 0 | AJ9: =Planning_Data!AJ7 -> 0 | AK9: =Planning_Data!AK7 -> 0 | ... AO9: =Planning_Data!AO7 -> 0
A10: Nr. | B10: Pos. | C10: Unit | D10: Kunde | E10: Projekt | F10: Angebotsdatum | G10: Titel | H10: Pos.-Titel | I10: Art | J10: Abrechnungsart | K10: Auftrag Status | L10: Position Status | M10: PT | N10: Nettosumme | O10: Eintrittswahrsch. in % | P10: gewichtete Nettosumme | Q10: fakturiert | R10: gewichtet offen | S10: vollständig fakturiert | T10: Debitorenrechnungen | U10: Leistungszeitraum | W10: Anzahl Monate | X10: Forecasttyp | Y10: Rest | Z10: Abweichung | AA10: Warnung | AB10: Beschreibung Status | AD10: Month 1 | AE10: Month 2 | AF10: Month 3 | AG10: Month 4 | AH10: Month 5 | AI10: Month 6 | AJ10: Month 7 | AK10: Month 8 | AL10: Month 9 | AM10: Month 10 | AN10: Month 11 | AO10: Month 12 | AP10: Erfassungsdatum | AQ10: Entscheidungsdatum | AR10: Zahlplan | AS10: Ansprechpartner | AT10: Strukturelement | AU10: Bemerkung | AV10: ProjectID | AW10: visible | AX10: visibleID

Sheet Grafiken 1

Sheet Grafiken 2

Sheet Projektübersicht
A1: Unit | B1: Kunde | C1: Projekt | D1: Forecast | E1: Plan | F1: Differenz Plan | G1: Vorjahr | H1: Differenz Vorjahr | I1: Vorvorjahr | J1: Differenz Vorvorjahr

Sheet Umsatz kumuliert
B1: =Forecast_Data!AD1 -> Month 1 | C1: =Forecast_Data!AE1 -> Month 2 | D1: =Forecast_Data!AF1 -> Month 3 | E1: =Forecast_Data!AG1 -> Month 4 | F1: =Forecast_Data!AH1 -> Month 5 | G1: =Forecast_Data!AI1 -> Month 6 | H1: =Forecast_Data!AJ1 -> Month 7 | I1: =Forecast_Data!AK1 -> Month 8 | ... M1: =Forecast_Data!AO1 -> Month 12
A2: IST | B2: =Forecast_Data!AD8 -> 0 | C2: =Forecast_Data!AE8 -> 0 | D2: =Forecast_Data!AF8 -> 0 | E2: =Forecast_Data!AG8 -> 0 | F2: =Forecast_Data!AH8 -> 0 | G2: =Forecast_Data!AI8 -> 0 | H2: =Forecast_Data!AJ8 -> 0 | I2: =Forecast_Data!AK8 -> 0 | ... M2: =Forecast_Data!AO8 -> 0
A3: Gesamt oben | B3: =Forecast_Data!AD7 -> 0 | C3: =Forecast_Data!AE7 -> 0 | D3: =Forecast_Data!AF7 -> 0 | E3: =Forecast_Data!AG7 -> 0 | F3: =Forecast_Data!AH7 -> 0 | G3: =Forecast_Data!AI7 -> 0 | H3: =Forecast_Data!AJ7 -> 0 | I3: =Forecast_Data!AK7 -> 0 | ... M3: =Forecast_Data!AO7 -> 0
A4: Gesamt | B4: =B2+B3 -> 0 | C4: =C2+C3 -> 0 | D4: =D2+D3 -> 0 | E4: =E2+E3 -> 0 | F4: =F2+F3 -> 0 | G4: =G2+G3 -> 0 | H4: =H2+H3 -> 0 | I4: =I2+I3 -> 0 | ... M4: =M2+M3 -> 0
A5: kumuliert | B5: =B4 -> 0 | C5: =B5+C4 -> 0 | D5: =C5+D4 -> 0 | E5: =D5+E4 -> 0 | F5: =E5+F4 -> 0 | G5: =F5+G4 -> 0 | H5: =G5+H4 -> 0 | I5: =H5+I4 -> 0 | J5: =I5+J4 -> 0 | ... M5: =L5+M4 -> 0
A6: Plan kumuliert | B6: =Forecast_Data!AD9 -> 0 | C6: =B6+Forecast_Data!AE9 -> 0 | D6: =C6+Forecast_Data!AF9 -> 0 | E6: =D6+Forecast_Data!AG9 -> 0 | F6: =E6+Forecast_Data!AH9 -> 0 | G6: =F6+Forecast_Data!AI9 -> 0 | H6: =G6+Forecast_Data!AJ9 -> 0 | I6: =H6+Forecast_Data!AK9 -> 0 | J6: =I6+Forecast_Data!AL9 -> 0 | ... M6: =L6+Forecast_Data!AO9 -> 0
A8: Vorjahr | B8: =SUMIFS('Rechnungen Vorjahr'!M:M, 'Rechnungen Vorjahr'!$Z:$Z, TRUE) -> 0 | C8: =SUMIFS('Rechnungen Vorjahr'!N:N, 'Rechnungen Vorjahr'!$Z:$Z, TRUE) -> 0 | D8: =SUMIFS('Rechnungen Vorjahr'!O:O, 'Rechnungen Vorjahr'!$Z:$Z, TRUE) -> 0 | E8: =SUMIFS('Rechnungen Vorjahr'!P:P, 'Rechnungen Vorjahr'!$Z:$Z, TRUE) -> 0 | F8: =SUMIFS('Rechnungen Vorjahr'!Q:Q, 'Rechnungen Vorjahr'!$Z:$Z, TRUE) -> 0 | G8: =SUMIFS('Rechnungen Vorjahr'!R:R, 'Rechnungen Vorjahr'!$Z:$Z, TRUE) -> 0 | H8: =SUMIFS('Rechnungen Vorjahr'!S:S, 'Rechnungen Vorjahr'!$Z:$Z, TRUE) -> 0 | I8: =SUMIFS('Rechnungen Vorjahr'!T:T, 'Rechnungen Vorjahr'!$Z:$Z, TRUE) -> 0 | J8: =SUMIFS('Rechnungen Vorjahr'!U:U, 'Rechnungen Vorjahr'!$Z:$Z, TRUE) -> 0 | K8: =SUMIFS('Rechnungen Vorjahr'!V:V, 'Rechnungen Vorjahr'!$Z:$Z, TRUE) -> 0 | L8: =SUMIFS('Rechnungen Vorjahr'!W:W, 'Rechnungen Vorjahr'!$Z:$Z, TRUE) -> 0 | M8: =SUMIFS('Rechnungen Vorjahr'!X:X, 'Rechnungen Vorjahr'!$Z:$Z, TRUE) -> 0
A9: Vorjahr kumuliert | B9: =B8 -> 0 | C9: =B9+C8 -> 0 | D9: =C9+D8 -> 0 | E9: =D9+E8 -> 0 | F9: =E9+F8 -> 0 | G9: =F9+G8 -> 0 | H9: =G9+H8 -> 0 | I9: =H9+I8 -> 0 | J9: =I9+J8 -> 0 | ... M9: =L9+M8 -> 0
A11: Vorvorjahr | B11: =SUMIFS('Rechnungen Vorvorjahr'!M:M, 'Rechnungen Vorvorjahr'!$Z:$Z, TRUE) -> 0 | C11: =SUMIFS('Rechnungen Vorvorjahr'!N:N, 'Rechnungen Vorvorjahr'!$Z:$Z, TRUE) -> 0 | D11: =SUMIFS('Rechnungen Vorvorjahr'!O:O, 'Rechnungen Vorvorjahr'!$Z:$Z, TRUE) -> 0 | E11: =SUMIFS('Rechnungen Vorvorjahr'!P:P, 'Rechnungen Vorvorjahr'!$Z:$Z, TRUE) -> 0 | F11: =SUMIFS('Rechnungen Vorvorjahr'!Q:Q, 'Rechnungen Vorvorjahr'!$Z:$Z, TRUE) -> 0 | G11: =SUMIFS('Rechnungen Vorvorjahr'!R:R, 'Rechnungen Vorvorjahr'!$Z:$Z, TRUE) -> 0 | H11: =SUMIFS('Rechnungen Vorvorjahr'!S:S, 'Rechnungen Vorvorjahr'!$Z:$Z, TRUE) -> 0 | I11: =SUMIFS('Rechnungen Vorvorjahr'!T:T, 'Rechnungen Vorvorjahr'!$Z:$Z, TRUE) -> 0 | J11: =SUMIFS('Rechnungen Vorvorjahr'!U:U, 'Rechnungen Vorvorjahr'!$Z:$Z, TRUE) -> 0 | K11: =SUMIFS('Rechnungen Vorvorjahr'!V:V, 'Rechnungen Vorvorjahr'!$Z:$Z, TRUE) -> 0 | L11: =SUMIFS('Rechnungen Vorvorjahr'!W:W, 'Rechnungen Vorvorjahr'!$Z:$Z, TRUE) -> 0 | M11: =SUMIFS('Rechnungen Vorvorjahr'!X:X, 'Rechnungen Vorvorjahr'!$Z:$Z, TRUE) -> 0
A12: Vorvorjahr kumuliert | B12: =B11 -> 0 | C12: =B12+C11 -> 0 | D12: =C12+D11 -> 0 | E12: =D12+E11 -> 0 | F12: =E12+F11 -> 0 | G12: =F12+G11 -> 0 | H12: =G12+H11 -> 0 | I12: =H12+I11 -> 0 | J12: =I12+J11 -> 0 | ... M12: =L12+M11 -> 0

Sheet Rechnungen
A1: Nr. | B1: Pos. | C1: Datum | D1: Kunde | E1: Projekt | F1: Betreff | G1: Positionstext | H1: Bezahldatum | I1: Leistungszeitraum | K1: Auftrag | L1: Netto | M1: Month 1 | N1: Month 2 | O1: Month 3 | P1: Month 4 | Q1: Month 5 | R1: Month 6 | S1: Month 7 | T1: Month 8 | U1: Month 9 | V1: Month 10 | W1: Month 11 | X1: Month 12 | Y1: ProjectID | Z1: visible

Sheet Rechnungen Vorjahr
A1: Nr. | B1: Pos. | C1: Datum | D1: Kunde | E1: Projekt | F1: Betreff | G1: Positionstext | H1: Bezahldatum | I1: Leistungszeitraum | K1: Auftrag | L1: Netto | M1: Month 1 | N1: Month 2 | O1: Month 3 | P1: Month 4 | Q1: Month 5 | R1: Month 6 | S1: Month 7 | T1: Month 8 | U1: Month 9 | V1: Month 10 | W1: Month 11 | X1: Month 12 | Y1: ProjectID | Z1: visible

Sheet Rechnungen Vorvorjahr
A1: Nr. | B1: Pos. | C1: Datum | D1: Kunde | E1: Projekt | F1: Betreff | G1: Positionstext | H1: Bezahldatum | I1: Leistungszeitraum | K1: Auftrag | L1: Netto | M1: Month 1 | N1: Month 2 | O1: Month 3 | P1: Month 4 | Q1: Month 5 | R1: Month 6 | S1: Month 7 | T1: Month 8 | U1: Month 9 | V1: Month 10 | W1: Month 11 | X1: Month 12 | Y1: ProjectID | Z1: visible

Sheet Planning_Data
A1: Nr. | B1: Pos. | C1: Unit | D1: Kunde | E1: Projekt | F1: Angebotsdatum | G1: Titel | H1: Pos.-Titel | I1: Art | J1: Abrechnungsart | K1: Auftrag Status | L1: Position Status | M1: PT | N1: Nettosumme | O1: Eintrittswahrsch. in % | P1: gewichtete Nettosumme | Q1: fakturiert | R1: gewichtet offen | S1: vollständig fakturiert | T1: Debitorenrechnungen | U1: Leistungszeitraum | W1: Anzahl Monate | X1: Forecasttyp | Y1: Rest | Z1: Abweichung | AA1: Warnung | AD1: Month 1 | AE1: Month 2 | AF1: Month 3 | AG1: Month 4 | AH1: Month 5 | AI1: Month 6 | AJ1: Month 7 | AK1: Month 8 | AL1: Month 9 | AM1: Month 10 | AN1: Month 11 | AO1: Month 12 | AP1: Erfassungsdatum | AQ1: Entscheidungsdatum | AR1: Zahlplan | AS1: Ansprechpartner | AT1: Strukturelement | AU1: Bemerkung | AV1: ProjectID | AW1: visible | AX1: unused
A2: date | AC2: beauftragt | AD2: =SUMIFS(AD11:AD100000,$L11:$L100000,"=beauftragt",$AW11:$AW100000, TRUE) -> 0 | AE2: =SUMIFS(AE11:AE100000,$L11:$L100000,"=beauftragt",$AW11:$AW100000, TRUE) -> 0 | AF2: =SUMIFS(AF11:AF100000,$L11:$L100000,"=beauftragt",$AW11:$AW100000, TRUE) -> 0 | AG2: =SUMIFS(AG11:AG100000,$L11:$L100000,"=beauftragt",$AW11:$AW100000, TRUE) -> 0 | AH2: =SUMIFS(AH11:AH100000,$L11:$L100000,"=beauftragt",$AW11:$AW100000, TRUE) -> 0 | AI2: =SUMIFS(AI11:AI100000,$L11:$L100000,"=beauftragt",$AW11:$AW100000, TRUE) -> 0 | AJ2: =SUMIFS(AJ11:AJ100000,$L11:$L100000,"=beauftragt",$AW11:$AW100000, TRUE) -> 0 | AK2: =SUMIFS(AK11:AK100000,$L11:$L100000,"=beauftragt",$AW11:$AW100000, TRUE) -> 0 | ... AO2: =SUMIFS(AO11:AO100000,$L11:$L100000,"=beauftragt",$AW11:$AW100000, TRUE) -> 0
AC3: gelegt | AD3: =SUMIFS(AD11:AD100000,$L11:$L100000,"=gelegt",$AW11:$AW100000, TRUE) -> 0 | AE3: =SUMIFS(AE11:AE100000,$L11:$L100000,"=gelegt",$AW11:$AW100000, TRUE) -> 0 | AF3: =SUMIFS(AF11:AF100000,$L11:$L100000,"=gelegt",$AW11:$AW100000, TRUE) -> 0 | AG3: =SUMIFS(AG11:AG100000,$L11:$L100000,"=gelegt",$AW11:$AW100000, TRUE) -> 0 | AH3: =SUMIFS(AH11:AH100000,$L11:$L100000,"=gelegt",$AW11:$AW100000, TRUE) -> 0 | AI3: =SUMIFS(AI11:AI100000,$L11:$L100000,"=gelegt",$AW11:$AW100000, TRUE) -> 0 | AJ3: =SUMIFS(AJ11:AJ100000,$L11:$L100000,"=gelegt",$AW11:$AW100000, TRUE) -> 0 | AK3: =SUMIFS(AK11:AK100000,$L11:$L100000,"=gelegt",$AW11:$AW100000, TRUE) -> 0 | ... AO3: =SUMIFS(AO11:AO100000,$L11:$L100000,"=gelegt",$AW11:$AW100000, TRUE) -> 0
AC4: LOI | AD4: =SUMIFS(AD11:AD100000,$L11:$L100000,"=LOI",$AW11:$AW100000, TRUE) -> 0 | AE4: =SUMIFS(AE11:AE100000,$L11:$L100000,"=LOI",$AW11:$AW100000, TRUE) -> 0 | AF4: =SUMIFS(AF11:AF100000,$L11:$L100000,"=LOI",$AW11:$AW100000, TRUE) -> 0 | AG4: =SUMIFS(AG11:AG100000,$L11:$L100000,"=LOI",$AW11:$AW100000, TRUE) -> 0 | AH4: =SUMIFS(AH11:AH100000,$L11:$L100000,"=LOI",$AW11:$AW100000, TRUE) -> 0 | AI4: =SUMIFS(AI11:AI100000,$L11:$L100000,"=LOI",$AW11:$AW100000, TRUE) -> 0 | AJ4: =SUMIFS(AJ11:AJ100000,$L11:$L100000,"=LOI",$AW11:$AW100000, TRUE) -> 0 | AK4: =SUMIFS(AK11:AK100000,$L11:$L100000,"=LOI",$AW11:$AW100000, TRUE) -> 0 | ... AO4: =SUMIFS(AO11:AO100000,$L11:$L100000,"=LOI",$AW11:$AW100000, TRUE) -> 0
AC5: in Erstellung | AD5: =SUMIFS(AD11:AD100000,$L11:$L100000,"=in Erstellung",$AW11:$AW100000, TRUE) -> 0 | AE5: =SUMIFS(AE11:AE100000,$L11:$L100000,"=in Erstellung",$AW11:$AW100000, TRUE) -> 0 | AF5: =SUMIFS(AF11:AF100000,$L11:$L100000,"=in Erstellung",$AW11:$AW100000, TRUE) -> 0 | AG5: =SUMIFS(AG11:AG100000,$L11:$L100000,"=in Erstellung",$AW11:$AW100000, TRUE) -> 0 | AH5: =SUMIFS(AH11:AH100000,$L11:$L100000,"=in Erstellung",$AW11:$AW100000, TRUE) -> 0 | AI5: =SUMIFS(AI11:AI100000,$L11:$L100000,"=in Erstellung",$AW11:$AW100000, TRUE) -> 0 | AJ5: =SUMIFS(AJ11:AJ100000,$L11:$L100000,"=in Erstellung",$AW11:$AW100000, TRUE) -> 0 | AK5: =SUMIFS(AK11:AK100000,$L11:$L100000,"=in Erstellung",$AW11:$AW100000, TRUE) -> 0 | ... AO5: =SUMIFS(AO11:AO100000,$L11:$L100000,"=in Erstellung",$AW11:$AW100000, TRUE) -> 0
AC6: Potenzial | AD6: =SUMIFS(AD11:AD100000,$L11:$L100000,"=Potenzial",$AW11:$AW100000, TRUE) -> 0 | AE6: =SUMIFS(AE11:AE100000,$L11:$L100000,"=Potenzial",$AW11:$AW100000, TRUE) -> 0 | AF6: =SUMIFS(AF11:AF100000,$L11:$L100000,"=Potenzial",$AW11:$AW100000, TRUE) -> 0 | AG6: =SUMIFS(AG11:AG100000,$L11:$L100000,"=Potenzial",$AW11:$AW100000, TRUE) -> 0 | AH6: =SUMIFS(AH11:AH100000,$L11:$L100000,"=Potenzial",$AW11:$AW100000, TRUE) -> 0 | AI6: =SUMIFS(AI11:AI100000,$L11:$L100000,"=Potenzial",$AW11:$AW100000, TRUE) -> 0 | AJ6: =SUMIFS(AJ11:AJ100000,$L11:$L100000,"=Potenzial",$AW11:$AW100000, TRUE) -> 0 | AK6: =SUMIFS(AK11:AK100000,$L11:$L100000,"=Potenzial",$AW11:$AW100000, TRUE) -> 0 | ... AO6: =SUMIFS(AO11:AO100000,$L11:$L100000,"=Potenzial",$AW11:$AW100000, TRUE) -> 0
AC7: Gesamt | AD7: =SUM(AD2:AD6)+AD8 -> 0 | AE7: =SUM(AE2:AE6)+AE8 -> 0 | AF7: =SUM(AF2:AF6)+AF8 -> 0 | AG7: =SUM(AG2:AG6)+AG8 -> 0 | AH7: =SUM(AH2:AH6)+AH8 -> 0 | AI7: =SUM(AI2:AI6)+AI8 -> 0 | AJ7: =SUM(AJ2:AJ6)+AJ8 -> 0 | AK7: =SUM(AK2:AK6)+AK8 -> 0 | ... AO7: =SUM(AO2:AO6)+AO8 -> 0
AC8: IST | AD8: =SUMIFS(Planning_Invoices!M:M, Planning_Invoices!$Z:$Z, TRUE) -> 0 | AE8: =SUMIFS(Planning_Invoices!N:N, Planning_Invoices!$Z:$Z, TRUE) -> 0 | AF8: =SUMIFS(Planning_Invoices!O:O, Planning_Invoices!$Z:$Z, TRUE) -> 0 | AG8: =SUMIFS(Planning_Invoices!P:P, Planning_Invoices!$Z:$Z, TRUE) -> 0 | AH8: =SUMIFS(Planning_Invoices!Q:Q, Planning_Invoices!$Z:$Z, TRUE) -> 0 | AI8: =SUMIFS(Planning_Invoices!R:R, Planning_Invoices!$Z:$Z, TRUE) -> 0 | AJ8: =SUMIFS(Planning_Invoices!S:S, Planning_Invoices!$Z:$Z, TRUE) -> 0 | AK8: =SUMIFS(Planning_Invoices!T:T, Planning_Invoices!$Z:$Z, TRUE) -> 0 | AL8: =SUMIFS(Planning_Invoices!U:U, Planning_Invoices!$Z:$Z, TRUE) -> 0 | AM8: =SUMIFS(Planning_Invoices!V:V, Planning_Invoices!$Z:$Z, TRUE) -> 0 | AN8: =SUMIFS(Planning_Invoices!W:W, Planning_Invoices!$Z:$Z, TRUE) -> 0 | AO8: =SUMIFS(Planning_Invoices!X:X, Planning_Invoices!$Z:$Z, TRUE) -> 0
A10: Nr. | B10: Pos. | C10: Unit | D10: Kunde | E10: Projekt | F10: Angebotsdatum | G10: Titel | H10: Pos.-Titel | I10: Art | J10: Abrechnungsart | K10: Auftrag Status | L10: Position Status | M10: PT | N10: Nettosumme | O10: Eintrittswahrsch. in % | P10: gewichtete Nettosumme | Q10: fakturiert | R10: gewichtet offen | S10: vollständig fakturiert | T10: Debitorenrechnungen | U10: Leistungszeitraum | W10: Anzahl Monate | X10: Forecasttyp | Y10: Rest | Z10: Abweichung | AA10: Warnung | AD10: Month 1 | AE10: Month 2 | AF10: Month 3 | AG10: Month 4 | AH10: Month 5 | AI10: Month 6 | AJ10: Month 7 | AK10: Month 8 | AL10: Month 9 | AM10: Month 10 | AN10: Month 11 | AO10: Month 12 | AP10: Erfassungsdatum | AQ10: Entscheidungsdatum | AR10: Zahlplan | AS10: Ansprechpartner | AT10: Strukturelement | AU10: Bemerkung | AV10: ProjectID | AW10: visible

Sheet Planning_Invoices
A1: Nr. | B1: Pos. | C1: Datum | D1: Kunde | E1: Projekt | F1: Betreff | G1: Positionstext | H1: Bezahldatum | I1: Leistungszeitraum | K1: Auftrag | L1: Netto | M1: Month 1 | N1: Month 2 | O1: Month 3 | P1: Month 4 | Q1: Month 5 | R1: Month 6 | S1: Month 7 | T1: Month 8 | U1: Month 9 | V1: Month 10 | W1: Month 11 | X1: Month 12 | Y1: ProjectID | Z1: visible

Sheet Info
A1: Date of creation
A2: Planning date
A3: Snapshot date
A4: Unused budget (T&M)
A5: Distribution of Forecast / Monatsverteilung
A6: The payment plan is used first, if available. Fixed price projects are scheduled at the end of the performance period. Time and materials and Flat-rate projects are distributed monthly during the performance period.
A8: Probality / Wahrscheinlichkeit
A9: The probability of an order (position) is determined by the following steps (beginning with step 1). The first matching entry is used. 'or value' means, that the probaility value given in the order is used, if given, otherwise the default probability value is assumed.
A11: Step | B11: Order state | C11: Position state | D11: Probability
A12: 1 | B12: DECLINED | C12: * | D12: 0
A13: 2 | B13: REPLACED | C13: * | D13: 0
A14: 3 | B14: * | C14: DECLINED | D14: 0
A15: 4 | B15: * | C15: REPLACED | D15: 0
A16: 5 | B16: * | C16: POTENTIAL | D16: 0 | E16: or value
A17: 6 | B17: * | C17: OPTIONAL | D17: 0 | E17: or value
A18: 7 | B18: * | C18: COMMISSIONED | D18: 1
A19: 8 | B19: POTENTIAL | C19: * | D19: 0 | E19: or value
A20: 9 | B20: COMPLETED | C20: * | D20: 1
A21: 10 | B21: COMMISSIONED | C21: * | D21: 1
A22: 11 | B22: ESCALATION, PLACED, BEEING_CREATED | C22: ESCALATION, PLACED, BEEING_CREATED | D22: 0.5 | E22: or value
A23: 12 | B23: ESCALATION, PLACED, BEEING_CREATED | C23: LOI | D23: 0.9 | E23: or value
A24: 13 | B24: LOI | C24: ESCALATION, PLACED, BEEING_CREATED, LOI | D24: 0.9 | E24: or value
A25: 14 | B25: * | C25: * | D25: 0 | E25: or value
A27: Schritt | B27: Auftragsstatus | C27: Positionsstatus | D27: Wahrscheinlichkeit
A28: 1 | B28: ABGELEHNT | C28: * | D28: 0
A29: 2 | B29: ERSETZT | C29: * | D29: 0
A30: 3 | B30: * | C30: ABGELEHNT | D30: 0
A31: 4 | B31: * | C31: ERSETZT | D31: 0
A32: 5 | B32: * | C32: POTENZIAL | D32: 0 | E32: oder Wert
A33: 6 | B33: * | C33: OPTIONAL | D33: 0 | E33: oder Wert
A34: 7 | B34: * | C34: BEAUFTRAGT | D34: 1
A35: 8 | B35: POTENZIAL | C35: * | D35: 0 | E35: oder Wert
A36: 9 | B36: ABGESCHLOSSEN | C36: * | D36: 1
A37: 10 | B37: BEAUFTRAGT | C37: * | D37: 1
A38: 11 | B38: ESKALATION, GELEGT, IN_ERSTELLUNG | C38: ESKALATION, GELEGT, IN_ERSTELLUNG | D38: 0.5 | E38: oder Wert
A39: 12 | B39: ESKALATION, GELEGT, IN_ERSTELLUNG | C39: LOI | D39: 0.9 | E39: oder Wert
A40: 13 | B40: LOI | C40: ESKALATION, GELEGT, IN_ERSTELLUNG, LOI | D40: 0.9 | E40: or value
A41: 14 | B41: * | C41: * | D41: 0 | E41: oder Wert
